algotik_tse/__init__.py
algotik_tse/settings.py
algotik_tse/core/__init__.py
algotik_tse/core/currency.py
algotik_tse/core/helper.py
algotik_tse/core/search.py
algotik_tse/core/shareholders.py
algotik_tse/core/stock.py
algotik_tse/core/stock_detail.py
algotik_tse/core/stock_list.py
algotik_tse/providers/__init__.py
algotik_tse/providers/tgju_convertor.py
algotik_tse-0.3.12.dist-info/AUTHORS.rst
algotik_tse-0.3.12.dist-info/LICENSE
algotik_tse-0.3.12.dist-info/METADATA
algotik_tse-0.3.12.dist-info/WHEEL
algotik_tse-0.3.12.dist-info/top_level.txt
algotik_tse-0.3.12.dist-info/RECORD
