Metadata-Version: 2.1
Name: algotik_tse
Version: 0.3.12
Summary: Get all data from TSETMC.com (Tehran Bourse).
Home-page: https://github.com/mohsenalipour/algotik_tse
Author: Mohsen Alipour
Author-email: alipour@algotik.ir
License: GNU General Public License v3
Keywords: algotik_tse
Classifier: Development Status :: 2 - Pre-Alpha
Classifier: Intended Audience :: Developers
Classifier: License :: OSI Approved :: GNU General Public License v3 (GPLv3)
Classifier: Natural Language :: English
Classifier: Programming Language :: Python :: 3
Classifier: Programming Language :: Python :: 3.6
Classifier: Programming Language :: Python :: 3.7
Classifier: Programming Language :: Python :: 3.8
Classifier: Programming Language :: Python :: 3.9
Classifier: Programming Language :: Python :: 3.10
Classifier: Programming Language :: Python :: 3.11
Classifier: Programming Language :: Python :: 3.12
Classifier: Programming Language :: Python :: 3.13
Requires-Python: >=3.6
License-File: LICENSE
License-File: AUTHORS.rst
Requires-Dist: requests
Requires-Dist: pandas
Requires-Dist: persiantools
Requires-Dist: lxml
